{"baseBpm":70,"musics":[{"bpm":70,"baseBeats":0.25,"scores":["(g.g1.b1)[L],d1[L],(g1.b1)[L],d1[L],(c1.g1.b1)[L],e1[L],(g1.a1)[L],g1[M],a1[M];(g.g1.b1)[L],d1[L],(g1.b1)[L],d1[L],(c1.g1.b1)[L],e1[L],(g1.a1)[K];(g.g1.b1)[L],d1[L],(g1.b1)[L],d1[L],(c1.g1.b1)[L],e1[L],(g1.a1)[LM],b1[M];(g.c1.e1.c2)[K],(g.b.d1.g1.b1)[K],(d.a.d1.#f1.a1)[K],d1[K];b1[L],a1[M],b1[M],U,a1[M],b1[M],U,V,a1[M],U,V,V;b1[L],a1[M],b1[M],V,b1[M],d2[M],b1[M],U,a1[M],a1[M],T;b1[L],a1[M],b1[M],U,a1[M],b1[M],U,V,a1[M],UV,V;c2[M],c2[L],b1[M],V,a1[M],g1[M],a1[M],T,U,b1[M],a1[M];g1[L],e1[M],g1[M],U,e2[M],d2[M],U,U,U,b1[M],a1[M];g1[L],e1[M],g1[M],U,e2[M],d2[M],U,U,U,b1[M],a1[M];","R;R;R;R;(g.g1.b1)[L],d1[L],(g1.b1)[L],d1[L],(c1.g1.b1)[L],e1[L],(g1.a1)[L],g1[M],a1[M];(g.g1.b1)[L],d1[L],(g1.b1)[L],d1[L],(c1.g1.b1)[L],e1[L],(g1.a1)[K];(g.g1.b1)[L],d1[L],(g1.b1)[L],d1[L],(c1.g1.b1)[L],e1[L],(c1.g1.a1)[LM],b1[M];(g.c1.e1.c2)[K],(g.b.d1.g1.b1)[K],(d.a.d1.#f1.a1)[K],d1[K];(c.e1.g1)[L],g[L],(e1.g1)[L],g[L],(e.d1.g1)[L],b[L],(d1.g1)[L],b[L];(c.e1.g1)[L],g[L],(e1.g1)[L],g[L],(e.d1.g1)[L],b[L],(d1.g1)[L],b[L];","R;R;R;R;R;R;R;R;R;R;","R;R;R;R;R;R;R;R;R;R;","R;R;R;R;R;R;R;R;c[J],e[J];c[J],e[J];"],"instruments":["piano","piano","Best_of_me_drum","best_of_me_drum","bass"],"alternatives":["piano","piano","drum","drum","bass"],"id":1},{"baseBeats":0.25,"scores":["g1[L],e1[M],g1[M],V,g1[M],e2[M],d2[M],U,V,b1[M],c2[M],b1[M],a1[L];a1[L],U,V,V,U,T,V,d2[M],d2[M],d2[M];b2[M],b2[M],b2[L],g2[L],b1[M],c2[M],U,V,c2[M],c2[M],c2[M],V,a2[M];V,a2[M],a2[M],#f2[M],V,d2[M],c2[M],b1[M],U,V,b1[M],V,a1[M],g1[M],g2[M];U,e2[M],g2[M],U,U,g2[L],a2[M],b2[M],V,a2[M],g2[M],a2[M];U,U,U,U,U,U,V,d2[M],d2[L];b2[M],b2[M],b2[L],g2[L],b1[M],c2[M],U,V,c2[M],c2[M],c2[M],V,a2[M];V,a2[M],a2[M],#f2[M],U,c2[M],b1[M],U,V,b1[M],V,a1[M],g1[M],g2[M];U,e2[M],g2[M],U,U,g2[L],a2[M],b2[M],V,a2[M],g2[M],a2[M];","(c.e1.g1)[L],g[L],(e1.g1)[L],g[L],(e.d1.g1)[L],b[L],(d1.g1)[L],b[L];(d.#f1.a1)[L],(c1.a1)[L],(a.d1)[M],(e1.g1)[M],c1[L],(d.d1.#f1)[K],D-1[K];(G-1.b.d1.g1)[L],d[L],(g.b.d1.g1)[L],d[L],(c.c1.e1)[L],g[L],(c1.e1)[L],g[L];(D-1.a.d1.#f1)[L],A-1[L],(#f.a.d1.#f1)[L],A-1[L],(G-1.b.d1.g1)[L],d[L],(#F-1.d1.a1)[L],d[L];(E-1.b.d1.g1)[L],B-1[L],(g.b.d1.g1)[L],B-1[L],(g.b.d1.g1)[L],B-1[L],(g.b.d1.g1)[L],B-1[L];(D-1.g.a.d1)[L],A-1[L],(d.g.a.d1)[L],(A-1.e1)[L],(D-1.#f.a.d1)[L],A-1[L],(#f.a.d1.#f1)[L],A-1[L];(G-1.b.d1.g1)[L],d[L],(g.b.d1.g1)[L],d[L],(c.c1.e1)[L],g[L],(c1.e1)[L],g[L];(D-1.a.d1.#f1)[L],A-1[L],(#f.a.d1.#f1)[L],A-1[L],(G-1.b.d1.g1)[L],d[L],(#F-1.d1.a1)[L],d[L];(E-1.b.d1.g1)[L],B-1[L],(g.b.d1.g1)[L],B-1[L],(g.b.d1.g1)[L],B-1[L],(g.b.d1.g1)[L],B-1[L];","R;S,T,d1[M],#c1[M],c1[L];#d1[M],V,d1[M],#c1[M],#d1[M],V,#c1[M],V,#d1[M],V,d1[M],#c1[M],#d1[M],V,#d1[M],V;#d1[M],V,d1[M],V,#d1[M],V,#c1[M],#c1[M],#d1[M],V,#c1[M],d1[M],#d1[M],V,d1[M],#c1[M];#d1[M],V,d1[M],#c1[M],#d1[M],V,#c1[M],V,#d1[M],V,d1[M],#c1[M],#d1[M],V,#d1[M],V;#d1[M],V,d1[M],V,#d1[M],V,d1[M],#c1[M],#d1[M],V,#c1[M],d1[M],d1[M],#c1[M],c1[L];#d1[M],V,d1[M],#c1[M],#d1[M],V,#c1[M],V,#d1[M],V,d1[M],#c1[M],#d1[M],V,#d1[M],V;#d1[M],V,d1[M],V,#d1[M],V,#c1[M],#c1[M],#d1[M],V,#c1[M],d1[M],#d1[M],V,d1[M],#c1[M];#d1[M],V,d1[M],#c1[M],#d1[M],V,#c1[M],V,#d1[M],V,d1[M],#c1[M],#d1[M],V,#d1[M],V;","R;R;C-1[M]{3},V,U,T,U,V,C-1[M],#C-1[M]{3},V,B-2[M]{3},V;C-1[M]{3},V,U,T,T,#C-1[M]{3},V,U;C-1[M]{3},V,U,T,U,V,C-1[M],#C-1[M]{3},V,B-2[M]{3},V;C-1[M]{3},V,U,#C-1[M]{3},V,U,T,U,V,B-2[M];C-1[M]{3},V,U,#C-1[M]{3},V,U,U,V,C-1[M],#C-1[M]{3},V,B-2[M]{3},V;C-1[M]{3},V,U,#C-1[M]{3},V,C-1[M]{3},V,C-1[M]{3},V,U,#C-1[M]{3},V,U;C-1[M]{3},V,U,#C-1[M]{3},V,U,U,V,C-1[M],#C-1[M]{3},V,B-2[M]{3},V;","c[J],e[J];d[JK],d[K];G-1[J],c[J];d[J],G-1[K],#F-1[K];E-1[J],e[J];d[JK],D-1[K];G-1[J],c[L],c[L],T;d[J],G-1[L],G-1[L],#F-1[K];E-1[K],T,E-1[L],e[KL];"],"instruments":["piano","piano","Best_of_me_drum","Best_of_me_drum","bass"],"alternatives":["piano","piano","drum","drum","bass"],"id":2,"bpm":70},{"baseBeats":0.25,"scores":["U,U,U,U,U,U,V,d2[M],d2[M],d2[M];b2[M],b2[M],b2[L],g2[L],b1[M],c2[M],U,U,c2[M],c2[M],V,a2[M];V,a2[M],a2[M],#f2[M],U,c2[M],b1[M],U,V,b1[M],V,a1[M],g1[M],g2[M];U,e2[M],g2[M],U,U,g2[M],V,a2[M],b2[M],V,a2[M],g2[M],a2[M];a2[L],U,U,U,U,U,U,a1[M],b1[M];c2[L],c2[M],c2[M],U,b1[M],c2[M],U,b1[M],a1[M],U,b1[M],g1[M];U,U,T,a1[M],a1[M],a1[M],a1[M],a1[L],g1[M],g1[M];U,b1[L],c2[L],b1[L],a1[L],V,g1[M],U,g1[M],a1[M];U,b1[L],c2[L],b1[L],a1[L],U,U,U;U,b1[L],c2[L],b1[L],a1[L],V,g1[M],U,U;g2[I];","(D-1.g.a.d1)[L],A-1[L],(d.g.a.d1)[L],(A-1.e1)[L],(D-1.#f.a.d1)[L],A-1[L],(#f.a.d1.#f1)[L],A-1[L];(G-1.b.d1.g1)[L]{5},d[L],(g.b.d1.g1)[L],d[L],(c.c1.e1)[L],g[L],(c1.e1)[L],g[L];(D-1.a.d1.#f1)[L],A-1[L],(#f.a.d1.#f1)[L],A-1[L],(G-1.b.d1.g1)[L],d[L],(#F-1.d1.a1)[L],d[L];(E-1.b.d1.g1)[L],B-1[L],(g.b.d1.g1)[L],B-1[L],(g.b.d1.g1)[L],B-1[L],(g.b.d1.g1)[L],B-1[L];(D-1.g.a.d1)[L],A-1[L],(d.g.a.d1)[L],(A-1.e1)[L],(D-1.#f.a.d1)[L],A-1[L],(#f.a.d1.#f1)[L],A-1[L];(F-1.a.c1)[L],c[L],(f.a.c1)[L],c[L],(F-1.a.c1.f1)[L],c[L],(f.a.c1.f1)[L],c[L];(E-1.b.e1.g1)[L],B-1[L],(g.b.e1.g1)[K],(D-1.d.a.d1.#f1)[J];(G-1.b.d1.g1)[L],d[L],(g.b.d1.g1)[L],d[L],(c.c1.e1.g1)[L],g[L],(c1.e1.g1)[L],g[L];(G-1.b.d1.g1)[L],d[L],(g.b.d1.g1)[L],d[L],(c.c1.e1.g1)[L],g[L],(c1.e1.g1)[L],g[L];(G-1.b.d1.g1)[L],d[L],(g.b.d1.g1)[L],d[L],(c.c1.e1.g1)[L],g[L],(c1.e1.g1)[L],g[L];(G-2.G-1.b.d1.g1.b1)[I]{6};","#d1[M],V,d1[M],V,#d1[M],V,d1[M],#c1[M],#d1[M],V,#c1[M],d1[M],T;#g[M],V,d1[M],V,#d1[M],V,d1[M],V,#d1[M],#a1[M],d1[M],V,#d1[M],V,d1[M],V;#d1[M],V,d1[M],V,#d1[M],V,d1[M],#a1[M],#d1[M],#a1[M],#d1[M],V,#d1[M],V,#A-1[M],V;#d1[M],V,d1[M],V,#d1[M],V,d1[M],V,#d1[M],#a1[M],d1[M],V,#d1[M],V,d1[M],V;#d1[M],V,d1[M],V,#d1[M],V,d1[M],#a1[M],#d1[M],#a1[M],#d1[M],V,#d1[M],V,#A-1[M],V;#g[M],V,d1[M],V,#d1[M],V,d1[M],V,#d1[M],#a1[M],d1[M],V,#d1[M],V,d1[M],V;#d1[M],V,d1[M],V,#d1[M],V,d1[M],V,#d1[M],V,#d1[M],V,#d1[M],V,d1[M],V;#g[M],V,d1[M],V,#d1[M],V,d1[M],V,#d1[M],#a1[M],d1[M],V,#d1[M],V,d1[M],V;#d1[M],V,d1[M],V,#d1[M],V,d1[M],#a1[M],#d1[M],#a1[M],#d1[M],V,#d1[M],V,#A-1[M],V;#d1[M],V,d1[M],V,#d1[M],V,d1[M],V,#d1[M],#a1[M],d1[M],V,#d1[M],V,d1[M],V;#c[M]{1},V,U,T,S;","C-1[M]{3},V,U,#C-1[M]{3},V,U,C-1[M]{3},V,U,#A-1[M],A-1[M]{2},G-1[M]{2},B-2[M]{3};C-1[M]{1},V,U,D-1[M]{1},V,C-1[M]{3},V,U,C-1[M]{3},V,D-1[M]{1},V,C-1[M]{3},V;C-1[M]{3},V,U,D-1[M]{1},V,C-1[M]{3},V,U,C-1[M]{3},V,D-1[M]{1},V,B-2[M]{3},V;C-1[M]{3},V,U,D-1[M]{1},V,C-1[M]{3},V,U,C-1[M]{3},V,D-1[M]{1},V,C-1[M]{3},V;C-1[M]{3},V,U,D-1[M]{1},V,C-1[M]{3},V,U,C-1[M]{3},V,D-1[M]{1},V,B-2[M]{3},V;C-1[M]{1},V,U,D-1[M]{1},V,C-1[M]{3},V,U,C-1[M]{3},V,D-1[M]{1},V,C-1[M]{3},V;C-1[M]{3},V,U,D-1[M]{1},V,C-1[M]{3},V,C-1[M]{3},V,V,B-2[M]{2},D-1[M]{1},B-2[M]{3},B-2[M]{2},V;C-1[M]{1},V,U,D-1[M]{1},V,C-1[M]{3},V,U,C-1[M]{3},V,D-1[M]{1},V,C-1[M]{3},V;C-1[M]{3},V,U,D-1[M]{1},V,C-1[M]{3},V,U,C-1[M]{3},V,D-1[M]{1},V,B-2[M]{3},V;C-1[M]{3},V,U,D-1[M]{1},V,C-1[M]{3},V,U,C-1[M]{3},V,D-1[M]{1},V,C-1[M]{3},V;R;","d[J],d[L],d[KL];G-1[J],c[L],c[KL];d[K],T,G-1[L],G-1[L],#F-1[K];E-1[J],e[L],e[KL];d[J],D-1[L],D-1[KL];f[K],T,f[L],f[KL];e[K],T,d[J];G-1[J],c[L],c[KL];G-1[J],c[L],c[KL];G-1[J],c[L],c[KL];G-1[I];"],"instruments":["piano","piano","Best_of_me_drum","Best_of_me_drum","bass"],"alternatives":["piano","piano","drum","drum","bass"],"id":3,"bpm":70}],"audition":{"start":[2,7],"end":[2,49]}}