[{"title":"Android网络编程","prefix":"第一章","remark":"","url":"","isTitle":true},{"title":"Android网络编程要学的东西与Http协议学习","prefix":"第一节","remark":"Android HTTP协议","url":"7.1.1.html","isTitle":false},{"title":"Android Http请求头与响应头的学习","prefix":"","remark":"1.1.1 Android Http 请求头与响应头(Request Response)","url":"7.1.2.html","isTitle":false},{"title":"Android HTTP请求方式: HttpURLConnection","prefix":"","remark":"1.1.2 Android Http请求方式: HttpURLConnection","url":"7.1.3.html","isTitle":false},{"title":"Android HTTP请求方式: HttpClient","prefix":"","remark":"1.1.3 Android Http请求方式：HttpClient","url":"7.1.4.html","isTitle":false},{"title":"Android XML数据解析","prefix":"第二节","remark":"Android XML","url":"7.2.1.html","isTitle":false},{"title":"Android JSON数据解析","prefix":"第三节","remark":"Android jSON","url":"7.2.2.html","isTitle":false},{"title":"Android文件上传与下载","prefix":"第四节","remark":"","url":"","isTitle":true},{"title":"Android 文件上传","prefix":"","remark":"1.4.1 Android 文件上传","url":"7.3.1.html","isTitle":false},{"title":"Android 文件下载（1）","prefix":"","remark":"1.4.2 Android 文件下载（1）","url":"7.3.2.html","isTitle":false},{"title":"Android 文件下载（2）","prefix":"","remark":"1.4.3 Android 文件下载（2）","url":"7.3.3.html","isTitle":false},{"title":"Android 调用 WebService","prefix":"第五节","remark":"Android WebService","url":"7.4.html","isTitle":false},{"title":"WebView(网页视图)基本用法","prefix":"第六节","remark":"Android WebView","url":"7.5.1.html","isTitle":false},{"title":"WebView和JavaScrip交互基础","prefix":"","remark":"1.6.1 WebView和JavaScrip交互基础","url":"7.5.2.html","isTitle":false},{"title":"Android 4.4后WebView的一些注意事项","prefix":"","remark":"1.6.2 Android 4.4后WebView的一些注意事项","url":"7.5.3.html","isTitle":false},{"title":"WebView文件下载","prefix":"","remark":"1.6.3 WebView文件下载","url":"7.5.4.html","isTitle":false},{"title":"WebView缓存问题","prefix":"","remark":"1.6.4 WebView缓存问题","url":"7.5.5.html","isTitle":false},{"title":"WebView处理网页返回的错误码信息","prefix":"","remark":"1.6.5 WebView处理网页返回的错误码信息","url":"7.5.6.html","isTitle":false},{"title":"Socket学习网络基础准备","prefix":"第七节","remark":"","url":"7.6.1.html","isTitle":false},{"title":"基于TCP协议的Socket通信(1)","prefix":"","remark":"1.7.1 基于TCP协议的Socket通信(1)","url":"7.6.2.html","isTitle":false},{"title":"基于TCP协议的Socket通信(2)","prefix":"","remark":"1.7.2 基于TCP协议的Socket通信(2)","url":"7.6.3.html","isTitle":false},{"title":"基于UDP协议的Socket通信","prefix":"","remark":"1.7.3 基于UDP协议的Socket通信","url":"7.6.4.html","isTitle":false},{"title":"Android图像、绘图与动画","prefix":"第二章","remark":"","url":"","isTitle":true},{"title":"Android Drawable图形","prefix":"第一节","remark":"","url":"","isTitle":true},{"title":"Android中的13种Drawable小结 Part 1","prefix":"","remark":"2.1.1 Android中的13种Drawable小结 Part 1","url":"8.1.1.html","isTitle":false},{"title":"Android中的13种Drawable小结 Part 2","prefix":"","remark":"2.1.2 Android中的13种Drawable小结 Part 2","url":"8.1.2.html","isTitle":false},{"title":"Android中的13种Drawable小结 Part 3","prefix":"","remark":"2.1.3 ndroid中的13种Drawable小结 Part 3","url":"8.1.3.html","isTitle":false},{"title":"Android Bitmap位图","prefix":"第二节","remark":"","url":"","isTitle":true},{"title":"Bitmap(位图)全解析 Part 1","prefix":"","remark":"2.2.1 Bitmap(位图)全解析 Part 1","url":"8.2.1.html","isTitle":false},{"title":"Bitmap引起的OOM问题","prefix":"","remark":"2.2.2 Bitmap引起的OOM问题","url":"8.2.2.html","isTitle":false},{"title":"Android 绘图工具","prefix":"第三节","remark":"","url":"","isTitle":true},{"title":"三个绘图工具类详解","prefix":"","remark":"2.3.1 三个绘图工具类详解","url":"8.3.1.html","isTitle":false},{"title":"绘图类实战示例","prefix":"","remark":"2.3.2 绘图类实战示例","url":"8.3.2.html","isTitle":false},{"title":"Paint API之—— MaskFilter(面具)","prefix":"","remark":"2.3.3 Paint API之—— MaskFilter(面具)","url":"8.3.3.html","isTitle":false},{"title":"Paint API之—— Xfermode与PorterDuff详解(一)","prefix":"","remark":"2.3.4 Paint API之—— Xfermode与PorterDuff详解(一)","url":"8.3.4.html","isTitle":false},{"title":"Paint API之—— Xfermode与PorterDuff详解(二)","prefix":"","remark":"2.3.5 Paint API之—— Xfermode与PorterDuff详解(二)","url":"8.3.5.html","isTitle":false},{"title":"Paint API之—— Xfermode与PorterDuff详解(三)","prefix":"","remark":"2.3.6 Paint API之—— Xfermode与PorterDuff详解(三)","url":"8.3.6.html","isTitle":false},{"title":"Paint API之—— Xfermode与PorterDuff详解(四)","prefix":"","remark":"2.3.7 Paint API之—— Xfermode与PorterDuff详解(四)","url":"8.3.7.html","isTitle":false},{"title":"Paint API之—— Xfermode与PorterDuff详解(五)","prefix":"","remark":"2.3.8 Paint API之—— Xfermode与PorterDuff详解(五)","url":"8.3.8.html","isTitle":false},{"title":"Paint API之—— ColorFilter(颜色过滤器)(1/3)","prefix":"","remark":"2.3.9 Paint API之—— ColorFilter(颜色过滤器)(1/3)","url":"8.3.9.html","isTitle":false},{"title":"Paint API之—— ColorFilter(颜色过滤器)(2-3)","prefix":"","remark":"2.3.10 Paint API之—— ColorFilter(颜色过滤器)(2-3)","url":"8.3.10.html","isTitle":false},{"title":"Paint API之—— ColorFilter(颜色过滤器)(3-3)","prefix":"","remark":"2.3.11 Paint API之—— ColorFilter(颜色过滤器)(3-3)","url":"8.3.11.html","isTitle":false},{"title":"Paint API之—— PathEffect(路径效果)","prefix":"","remark":"2.3.12 Paint API之—— PathEffect(路径效果)","url":"8.3.12.html","isTitle":false},{"title":"Paint API之—— Shader(图像渲染)","prefix":"","remark":"2.3.13 Paint API之—— Shader(图像渲染)","url":"8.3.13.html","isTitle":false},{"title":"Paint几个枚举/常量值以及ShadowLayer阴影效果","prefix":"","remark":"2.3.14 Paint几个枚举/常量值以及ShadowLayer阴影效果","url":"8.3.14.html","isTitle":false},{"title":"Paint API之——Typeface(字型)","prefix":"","remark":"2.3.15 Paint API之——Typeface(字型)","url":"8.3.15.html","isTitle":false},{"title":"Canvas API详解(Part 1)","prefix":"","remark":"2.3.16 Canvas API详解(Part 1)","url":"8.3.16.html","isTitle":false},{"title":"Canvas API详解(Part 2)剪切方法合集","prefix":"","remark":"2.3.17 Canvas API详解(Part 2)剪切方法合集","url":"8.3.17.html","isTitle":false},{"title":"Canvas API详解(Part 3)Matrix和drawBitmapMesh","prefix":"","remark":"2.3.18 Canvas API详解(Part 3)Matrix和drawBitmapMesh","url":"8.3.18.html","isTitle":false},{"title":"Android 动画工具","prefix":"第四节","remark":"","url":"","isTitle":true},{"title":"Android动画合集之帧动画","prefix":"","remark":"2.4.1 Android动画合集之帧动画","url":"8.4.1.html","isTitle":false},{"title":"Android动画合集之补间动画","prefix":"","remark":"2.4.2 Android动画合集之补间动画","url":"8.4.2.html","isTitle":false},{"title":"Android动画合集之属性动画-初见","prefix":"","remark":"2.4.3 Android动画合集之属性动画-初见","url":"8.4.3.html","isTitle":false},{"title":"Android动画合集之属性动画-又见","prefix":"","remark":"2.4.4 Android动画合集之属性动画-又见","url":"8.4.4.html","isTitle":false},{"title":"Android多媒体开发","prefix":"第三章","remark":"","url":"","isTitle":true},{"title":"使用SoundPool播放音效(Duang~)","prefix":"第一节","remark":"Android SoundPool","url":"9.1.html","isTitle":false},{"title":"使用MediaPlayer播放音频与视频","prefix":"第二节","remark":"Android MediaPlayer","url":"9.2.html","isTitle":false},{"title":"使用Camera拍照","prefix":"第三节","remark":"Android Camera","url":"9.3.html","isTitle":false},{"title":"使用MediaRecord录音","prefix":"第四节","remark":"Android MediaRecord","url":"9.4.html","isTitle":false},{"title":"Android硬件服务相关内容","prefix":"第四章","remark":"","url":"","isTitle":true},{"title":"TelephonyManager(电话管理器)","prefix":"第一节","remark":"Android TelephonyManager","url":"10.1.html","isTitle":false},{"title":"SmsManager(短信管理器)","prefix":"第二节","remark":"Android SmsManager","url":"10.2.html","isTitle":false},{"title":"AudioManager(音频管理器)","prefix":"第三节","remark":"Android AudioManager","url":"10.3.html","isTitle":false},{"title":"Vibrator(振动器)","prefix":"第四节","remark":"Android Vibrator","url":"10.4.html","isTitle":false},{"title":"AlarmManager(闹钟服务)","prefix":"第五节","remark":"Android AlarmManager","url":"10.5.html","isTitle":false},{"title":"PowerManager(电源服务)","prefix":"第六节","remark":"Android PowerManager","url":"10.6.html","isTitle":false},{"title":"WindowManager(窗口管理服务)","prefix":"第七节","remark":"Android WindowManager","url":"10.7.html","isTitle":false},{"title":"LayoutInflater(布局服务)","prefix":"第八节","remark":"Android LayoutInflater","url":"10.8.html","isTitle":false},{"title":"WallpaperManager(壁纸管理器)","prefix":"第九节","remark":"Android WallpaperManager","url":"10.9.html","isTitle":false},{"title":"传感器专题(1)——相关介绍","prefix":"第十节","remark":"Android 传感器专题","url":"10.10.html","isTitle":false},{"title":"传感器专题(2)——方向传感器","prefix":"第十一节","remark":"Android 传感器专题","url":"10.11.html","isTitle":false},{"title":"传感器专题(3)——加速度/陀螺仪传感器","prefix":"第十二节","remark":"Android 传感器专题","url":"10.12.html","isTitle":false},{"title":"传感器专题(4)——其他传感器了解","prefix":"第十三节","remark":"Android 传感器专题","url":"10.13.html","isTitle":false},{"title":"Android GPS初涉","prefix":"第十四节","remark":"Android GPS","url":"10.14.html","isTitle":false}]